lightshow/__init__.py
lightshow/_version.py
lightshow/database.py
lightshow/defaults.py
lightshow/pymatgen_utils.py
lightshow/_tests/__init__.py
lightshow/_tests/conftest.py
lightshow/_tests/test_broaden.py
lightshow/_tests/test_database.py
lightshow/_tests/test_exciting.py
lightshow/_tests/test_fdmnes.py
lightshow/_tests/test_metadata.py
lightshow/_tests/dummy_chpsp_files/Core_O.wfc
lightshow/_tests/dummy_chpsp_files/Core_Ti.wfc
lightshow/_tests/dummy_chpsp_files/O.fch.upf
lightshow/_tests/dummy_chpsp_files/Ti.fch.upf
lightshow/_tests/dummy_potcar_files/O_GW/POTCAR
lightshow/_tests/dummy_potcar_files/Ti_sv_GW/POTCAR
lightshow/_tests/dummy_psp_files/O.mock.upf
lightshow/_tests/dummy_psp_files/Ti.mock.upf
lightshow/_tests/dummy_psp_files/mock_cutoff_table.json
lightshow/_tests/helpers/__init__.py
lightshow/_tests/helpers/geometry.py
lightshow/_tests/sample_files/README.rst
lightshow/_tests/sample_files/ene_dep_broad.txt
lightshow/_tests/sample_files/gauss_broad.txt
lightshow/_tests/sample_files/lorentz_broad.txt
lightshow/_tests/sample_files/voigt_broad.txt
lightshow/_tests/structure_files/mp-10734/POSCAR
lightshow/_tests/structure_files/mp-1215/POSCAR
lightshow/_tests/structure_files/mp-1840/POSCAR
lightshow/_tests/structure_files/mp-2657/POSCAR
lightshow/_tests/structure_files/mp-2664/POSCAR
lightshow/_tests/structure_files/mp-390/POSCAR
lightshow/_tests/structure_files/mp-430/POSCAR
lightshow/_tests/structure_files/mp-458/POSCAR
lightshow/common/__init__.py
lightshow/common/kpoints.py
lightshow/common/nbands.py
lightshow/parameters/__init__.py
lightshow/parameters/_base.py
lightshow/parameters/exciting.py
lightshow/parameters/fdmnes.py
lightshow/parameters/feff.py
lightshow/parameters/ocean.py
lightshow/parameters/vasp.py
lightshow/parameters/xspectra.py
lightshow/postprocess/__init__.py
lightshow/postprocess/broaden.py
lightshow/postprocess/compare_utils.py
lightshow/postprocess/parse.py
lightshow/utils/__init__.py
lightshow/utils/environ_utils.py
lightshow-1.2.8.dist-info/METADATA
lightshow-1.2.8.dist-info/WHEEL
lightshow-1.2.8.dist-info/licenses/AUTHORS.md
lightshow-1.2.8.dist-info/licenses/LICENSE
lightshow-1.2.8.dist-info/RECORD
