Metadata-Version: 2.3
Name: lightshow
Version: 1.2.8
Summary: A one-stop-shop for computational spectroscopy
Author: Fanchen Meng, Deyu Lu, Benedikt Maurer, Fabien Peschel, Eli Stavitski, John T. Vinson, Christian Vorwerk
Author-email: "Matthew R. Carbone" <mcarbone@bnl.gov>, Xiaohui Qu <xiaqu@bnl.gov>
Maintainer-email: "Matthew R. Carbone" <mcarbone@bnl.gov>, Xiaohui Qu <xiaqu@bnl.gov>
Classifier: Development Status :: 2 - Pre-Alpha
Classifier: Intended Audience :: Developers
Classifier: Intended Audience :: Education
Classifier: Intended Audience :: Science/Research
Classifier: Natural Language :: English
Classifier: Programming Language :: Python :: 3
Classifier: Programming Language :: Python :: 3 :: Only
Classifier: Topic :: Scientific/Engineering
Requires-Python: >=3.9
Requires-Dist: ase>=3.23.0
Requires-Dist: monty>=2024.10.21
Requires-Dist: mp-api==0.41.2
Requires-Dist: numpy>=1.26.4
Requires-Dist: pydantic-core<=2.23.4
Requires-Dist: pydantic<=2.9.2
Requires-Dist: pymatgen==2024.3.1
Requires-Dist: tqdm>=4.67.0
Provides-Extra: all
Requires-Dist: coverage>=7.6.7; extra == 'all'
Requires-Dist: dunamai>=1.23.0; extra == 'all'
Requires-Dist: flake8>=7.1.1; extra == 'all'
Requires-Dist: ipython>=8.18.1; extra == 'all'
Requires-Dist: jupyterlab>=4.3.1; extra == 'all'
Requires-Dist: matplotlib>=3.9.2; extra == 'all'
Requires-Dist: myst-parser>=3.0.1; extra == 'all'
Requires-Dist: nbstripout>=0.8.1; extra == 'all'
Requires-Dist: numpydoc>=1.8.0; extra == 'all'
Requires-Dist: pytest-cov>=6.0.0; extra == 'all'
Requires-Dist: pytest>=8.3.3; extra == 'all'
Requires-Dist: ruff>=0.7.4; extra == 'all'
Requires-Dist: sphinx-autobuild>=2024.10.3; extra == 'all'
Requires-Dist: sphinx-copybutton>=0.5.2; extra == 'all'
Requires-Dist: sphinx>=7.4.7; extra == 'all'
Provides-Extra: doc
Requires-Dist: myst-parser>=3.0.1; extra == 'doc'
Requires-Dist: numpydoc>=1.8.0; extra == 'doc'
Requires-Dist: sphinx-autobuild>=2024.10.3; extra == 'doc'
Requires-Dist: sphinx-copybutton>=0.5.2; extra == 'doc'
Requires-Dist: sphinx>=7.4.7; extra == 'doc'
Provides-Extra: extras
Requires-Dist: dunamai>=1.23.0; extra == 'extras'
Requires-Dist: ipython>=8.18.1; extra == 'extras'
Requires-Dist: jupyterlab>=4.3.1; extra == 'extras'
Requires-Dist: matplotlib>=3.9.2; extra == 'extras'
Provides-Extra: test
Requires-Dist: coverage>=7.6.7; extra == 'test'
Requires-Dist: flake8>=7.1.1; extra == 'test'
Requires-Dist: nbstripout>=0.8.1; extra == 'test'
Requires-Dist: pytest-cov>=6.0.0; extra == 'test'
Requires-Dist: pytest>=8.3.3; extra == 'test'
Requires-Dist: ruff>=0.7.4; extra == 'test'
